CHANGELOG.txt
LICENCE.txt
MANIFEST.in
README.txt
setup.py
AddTwoNumbers/BasicFunction.py
AddTwoNumbers/__init__.py
HrushikeshPatilSum.egg-info/PKG-INFO
HrushikeshPatilSum.egg-info/SOURCES.txt
HrushikeshPatilSum.egg-info/dependency_links.txt
HrushikeshPatilSum.egg-info/top_level.txt